{
  "project_info": {
    "project_number": "705985875474",
    "firebase_url": "https://flutter-sample-b2c24.firebaseio.com",
    "project_id": "flutter-sample-b2c24",
    "storage_bucket": "flutter-sample-b2c24.appspot.com"
  },
  "client": [
    {
      "client_info": {
        "mobilesdk_app_id": "1:705985875474:android:885cd8430492dca1cb12cb",
        "android_client_info": {
          "package_name": "com.example.firebase_ml_flutter_sample"
        }
      },
      "oauth_client": [
        {
          "client_id": "705985875474-f6dr840k5pfvedjgmfr628ae452rgjcm.apps.googleusercontent.com",
          "client_type": 3
        }
      ],
      "api_key": [
        {
          "current_key": "AIzaSyB9fTvOBXtGDRLuOyIN479IEWgkm7hixgE"
        }
      ],
      "services": {
        "appinvite_service": {
          "other_platform_oauth_client": [
            {
              "client_id": "705985875474-f6dr840k5pfvedjgmfr628ae452rgjcm.apps.googleusercontent.com",
              "client_type": 3
            }
          ]
        }
      }
    }
  ],
  "configuration_version": "1"
}